{
  "openapi": "3.0.4",
  "info": {
    "title": "PatientAPI",
    "version": "1.0"
  },
  "paths": {
    "/api/Patient": {
      "get": {
        "tags": [
          "Patient"
        ],
        "parameters": [
          {
            "name": "patientId",
            "in": "query",
            "schema": {
              "type": "integer",
              "format": "int32"
            }
          }
        ],
        "responses": {
          "200": {
            "description": "OK"
          }
        }
      }
    }
  },
  "components": { }
}